hello-world.py
hello_world.py
hello_world_baxter2-0.0.4.dist-info/LICENSE.txt
hello_world_baxter2-0.0.4.dist-info/METADATA
hello_world_baxter2-0.0.4.dist-info/WHEEL
hello_world_baxter2-0.0.4.dist-info/top_level.txt
hello_world_baxter2-0.0.4.dist-info/RECORD
