Metadata-Version: 2.1
Name: hello-world-baxter2
Version: 0.0.4
Summary: UNKNOWN
Home-page: https://github.com/baxter2/hello-world-baxter2
Author: Baxter Callan
Author-email: baxcallan@gmail.com
License: UNKNOWN
Platform: UNKNOWN
Classifier: Programming Language :: Python :: 3
Classifier: Programming Language :: Python :: 3.6
Classifier: Programming Language :: Python :: 3.7
Classifier: License :: OSI Approved :: MIT License
Classifier: Operating System :: OS Independent
